fzf_template/__init__.py
fzf_template/__main__.py
fzf_template/fzf_template.py
fzf_template-0.1.0.dist-info/AUTHORS.rst
fzf_template-0.1.0.dist-info/LICENSE
fzf_template-0.1.0.dist-info/METADATA
fzf_template-0.1.0.dist-info/WHEEL
fzf_template-0.1.0.dist-info/entry_points.txt
fzf_template-0.1.0.dist-info/top_level.txt
fzf_template-0.1.0.dist-info/RECORD
