Metadata-Version: 2.1
Name: fzf-template
Version: 0.1.0
Summary: Template files using yaml config and an fzf selector
Home-page: https://github.com/shanedabes/fzf_template
Author: Shane Donohoe
Author-email: shane@donohoe.cc
License: BSD license
Keywords: fzf_template
Platform: UNKNOWN
Classifier: Intended Audience :: Developers
Classifier: License :: OSI Approved :: BSD License
Classifier: Natural Language :: English
Classifier: Programming Language :: Python :: 3
Classifier: Programming Language :: Python :: 3.6
Classifier: Programming Language :: Python :: 3.7
Requires-Dist: iterfzf (==0.4.0.17.3)
